{
    "structures": [
        {
            "name": "BinTree",
            "points": 1,
            "commands": 
            [
                {
                    "name": "P1",
                    "key": "c"
                },
                {
                    "name": "P2",
                    "key": "d"
                }
            ],
            "unlocked": true,
            "key": "B"
        },
        {
            "name": "Queue",
            "points": 1,
            "commands": [
                {
                    "name": "P1",
                    "key": "h"
                },
                {
                    "name": "P2",
                    "key": "r"
                }
            ],
            "unlocked": true,
            "key": "Q"
        },
        {
            "name": "Stack",
            "points": 3,
            "commands": [
                {
                    "name": "P1",
                    "key": "m"
                },
                {
                    "name": "P2",
                    "key": "e"
                }
            ],
            "unlocked": false,
            "key": "S"
        },
        {
            "name": "List",
            "points": 2,
            "commands": [
                {
                    "name": "P1",
                    "key": "l"
                },
                {
                    "name": "P2",
                    "key": "r"
                }
            ],
            "unlocked": true,
            "key": "L"
        },
        {
            "name": "Map",
            "points": 4,
            "commands": [
                {
                    "name": "P1",
                    "key": "c"
                },
                {
                    "name": "P2",
                    "key": "p"
                }
            ],
            "unlocked": false,
            "key": "M"
        },
        {
            "name": "Arbol_avl",
            "points": 5,
            "commands": [
                {
                    "name": "P1",
                    "key": "q"
                },
                {
                    "name": "P2",
                    "key": "w"
                }
            ],
            "unlocked": false,
            "key": "A"
        },
        {
            "name": "DiGraph",
            "points": 3,
            "commands": [
                {
                    "name": "P1",
                    "key": "m"
                },
                {
                    "name": "P2",
                    "key": "t"
                }
            ],
            "unlocked": false,
            "key": "D"
        }
    ]
}